dqpu/__init__.py
dqpu/cli.py
dqpu/samplernode.py
dqpu/utils.py
dqpu/verifiernode.py
dqpu/backends/__init__.py
dqpu/backends/base.py
dqpu/backends/qiskit/__init__.py
dqpu/backends/qiskit/dqpubackend.py
dqpu/backends/qiskit/dqpujob.py
dqpu/backends/qiskit/dqpuprovider.py
dqpu/blockchain/__init__.py
dqpu/blockchain/blockchain.py
dqpu/blockchain/ipfs_gateway.py
dqpu/blockchain/near.py
dqpu/q/__init__.py
dqpu/q/circuit.py
dqpu/q/gate.py
dqpu/q/gates.py
dqpu/q/utils.py
dqpu/sampler/__init__.py
dqpu/sampler/aersimulatorsampler.py
dqpu/sampler/dasksimulatorsampler.py
dqpu/sampler/sampler.py
dqpu/verifier/__init__.py
dqpu/verifier/basictrapper.py
dqpu/verifier/trapper.py
dqpu/verifier/verifier.py
dqpu-0.1.dist-info/LICENSE
dqpu-0.1.dist-info/METADATA
dqpu-0.1.dist-info/WHEEL
dqpu-0.1.dist-info/entry_points.txt
dqpu-0.1.dist-info/top_level.txt
dqpu-0.1.dist-info/RECORD
